shamir/__init__.py
shamir/_version.py
shamir/errors.py
shamir/math/__init__.py
shamir/utils/__init__.py
horcrux-1.0.7.dist-info/METADATA
horcrux-1.0.7.dist-info/WHEEL
horcrux-1.0.7.dist-info/licenses/LICENSE
horcrux-1.0.7.dist-info/RECORD
