Metadata-Version: 2.4
Name: horcrux
Version: 1.0.7
Summary: A Python implementation of Shamir's Secret Sharing
Project-URL: Homepage, https://github.com/reidhoch/horcrux
Project-URL: Repository, https://github.com/reidhoch/horcrux
Project-URL: Documentation, https://github.com/reidhoch/horcrux#readme
Project-URL: Bug Tracker, https://github.com/reidhoch/horcrux/issues
Project-URL: Changelog, https://github.com/reidhoch/horcrux/releases
Author-email: Reid Hochstedler <reidhoch@gmail.com>
License: MPL-2.0
License-File: LICENSE
Keywords: cryptography,secret-sharing,security,shamir,vault
Classifier: Development Status :: 5 - Production/Stable
Classifier: Intended Audience :: Developers
Classifier: Programming Language :: Python :: 3
Classifier: Programming Language :: Python :: 3 :: Only
Classifier: Programming Language :: Python :: 3.11
Classifier: Programming Language :: Python :: 3.12
Classifier: Programming Language :: Python :: 3.13
Classifier: Programming Language :: Python :: 3.14
Classifier: Topic :: Security
Classifier: Topic :: Security :: Cryptography
Classifier: Topic :: Software Development :: Libraries :: Python Modules
Classifier: Typing :: Typed
Requires-Python: >=3.11
